[
    {
        "id": 1,
        "username": "Admin",
        "password": "$2b$12$9kEUt8dpAUzO0LwTjKacO.lXqbPDmc0UswjA0QVoyRd/YXxuFTdse",
        "first_name": "System",
        "last_name": "Admin",
        "date_joined": "2024-01-01",
        "birth_date": "1991-01-01",
        "is_organiser": false,
        "is_active": true,
        "is_authenticated": true,
        "is_superuser": true
    },
    {
        "id": 2,
        "username": "Profound Decisions",
        "password": "$2b$12$FDowck5pDwBIhazT/D.iBesSc7MWjhG1pKebcM8cUst3bwqvZ2veG",
        "first_name": "Profound",
        "last_name": "Decisions",
        "about": "A Live Action Roleplaying Game company based in the UK. We run the Empire LRP game.",
        "website": "https://www.profounddecisions.co.uk",
        "date_joined": "2024-01-01",
        "birth_date": "1991-01-01",
        "is_organiser": true,
        "is_active": true,
        "is_authenticated": true,
        "is_superuser": false
    },
    {
        "id": 3,
        "username": "Curious Pastimes",
        "password": "$2b$12$/eKwaiu3LMojIvHXmtsoX.8Q5A6QwhOr2s./D6I7IDS8uFWwMf8Wa",
        "first_name": "Curious",
        "last_name": "Pastimes",
        "about": "A Live Action Roleplaying Game company based in the UK. We run the Curious Pastimes LRP game.",
        "website": "https://www.curiouspastimes.co.uk",
        "date_joined": "2024-01-01",
        "birth_date": "1991-01-01",
        "is_organiser": true,
        "is_active": true,
        "is_authenticated": true,
        "is_superuser": false
    },
    {
        "id": 4,
        "username": "Fools And Heroes",
        "password": "$2b$12$g7N0hGEs0lC2mzKsqiS2uu3OS/13m9qm2fUVfB2wVpFm8cKZ6aBKK",
        "first_name": "Fools",
        "last_name": "Heroes",
        "about": "A Live Action Roleplaying Game Society based in the UK. We run the Fools and Heroes LRP game.",
        "website": "https://www.foolsandheroes.org",
        "date_joined": "2024-01-01",
        "birth_date": "1991-01-01",
        "is_organiser": true,
        "is_active": true,
        "is_authenticated": true,
        "is_superuser": false
    },
    {
        "id": 5,
        "username": "Lorien Trust",
        "password": "$2b$12$nKhLy.nxgpIpVSvTpVfoXOwLyBuMVpTDNSvsX9AahIP2/vR0JOUki",
        "first_name": "Lorien",
        "last_name": "Trust",
        "about": "A Live Action Roleplaying Game company based in the UK. We run the Lorien Trust LRP game.",
        "website": "https://www.lorientrust.com",
        "date_joined": "2024-01-01",
        "birth_date": "1991-01-01",
        "is_organiser": true,
        "is_active": true,
        "is_authenticated": true,
        "is_superuser": false
    }
]